MANIFEST.in
README.md
setup.py
openformat/__init__.py
openformat/util.py
openformat.egg-info/PKG-INFO
openformat.egg-info/SOURCES.txt
openformat.egg-info/dependency_links.txt
openformat.egg-info/requires.txt
openformat.egg-info/top_level.txt
openformat/mims/__init__.py
openformat/mims/structures.py
openformat/sp/__init__.py