Metadata-Version: 2.1
Name: openformat
Version: 0.3.0
Summary: UNKNOWN
Home-page: UNKNOWN
Author: Till Hoffmann, Mary Burkitt-Gray
License: UNKNOWN
Platform: UNKNOWN
